collage_maker/__init__.py
collage_maker-0.1.1.dist-info/LICENSE
collage_maker-0.1.1.dist-info/METADATA
collage_maker-0.1.1.dist-info/WHEEL
collage_maker-0.1.1.dist-info/top_level.txt
collage_maker-0.1.1.dist-info/RECORD
