Metadata-Version: 2.1
Name: collage-maker
Version: 0.1.1
Summary: image collage maker
Home-page: https://github.com/mtroym/image_collage_maker
Author: Yiming Mao
Author-email: maoym.troy@gmail.com
License: MIT Licence
Keywords: image,image collage
Platform: any
Requires-Python: >=3.6.8
Requires-Dist: opencv-python
Requires-Dist: opencv-contrib-python
Requires-Dist: numpy
